Metadata-Version: 2.1
Name: spectre-cnv
Version: 0.2.1
Summary: Long read copy number variation (CNV) caller
Home-page: https://github.com/fritzsedlazeck/Spectre
Author: Philippe Sanio
Author-email: philippe.sanio@gmail.com
License: MIT
License-File: LICENSE
License-File: LICENSE.md
Requires-Dist: pysam >=0.22.0
Requires-Dist: numpy >=1.24.3
Requires-Dist: pandas >=2.0.1
Requires-Dist: matplotlib >=3.7.1
Requires-Dist: scipy >=1.10.1
